geochemistrypy/__init__.py
geochemistrypy/global_variable.py
geochemistrypy/client/__init__.py
geochemistrypy/client/main.py
geochemistrypy/client/tmp.py
geochemistrypy/client/dataset/Data_Classification.xlsx
geochemistrypy/client/dataset/Data_Clustering.xlsx
geochemistrypy/client/dataset/Data_Decomposition.xlsx
geochemistrypy/client/dataset/Data_Regression.xlsx
geochemistrypy/data/__init__.py
geochemistrypy/data/data_readiness.py
geochemistrypy/data/feature_engineering.py
geochemistrypy/data/imputation.py
geochemistrypy/data/statistic.py
geochemistrypy/model/__init__.py
geochemistrypy/model/classification.py
geochemistrypy/model/clustering.py
geochemistrypy/model/decomposition.py
geochemistrypy/model/regression.py
geochemistrypy/plot/__init__.py
geochemistrypy/plot/geochemistry_plot.py
geochemistrypy/plot/map_plot.py
geochemistrypy/plot/statistic_plot.py
geochemistrypy/process/__init__.py
geochemistrypy/process/classify.py
geochemistrypy/process/cluster.py
geochemistrypy/process/decompose.py
geochemistrypy/process/regress.py
geochemistrypy/tests/__init__.py
geochemistrypy/tests/test_data/__init__.py
geochemistrypy/tests/test_data/test_data_readiness.py
geochemistrypy/utils/__init__.py
geochemistrypy/utils/base.py
geochemistrypy/utils/exceptions.py
geochemistrypy-0.0.1.dist-info/METADATA
geochemistrypy-0.0.1.dist-info/WHEEL
geochemistrypy-0.0.1.dist-info/licenses/LICENSE
geochemistrypy-0.0.1.dist-info/RECORD
