Metadata-Version: 2.1
Name: geochemistrypy
Version: 0.0.1
Summary: A Python framework for data-driven geochemistry discovery
Project-URL: Homepage, https://github.com/ZJUEarthData/geochemistrypy
Project-URL: Bug Tracker, https://github.com/ZJUEarthData/geochemistrypy/issues
Author-email: Can He <sanyhew1097618435@163.com>
License: MIT License
Classifier: License :: OSI Approved :: MIT License
Classifier: Operating System :: OS Independent
Classifier: Programming Language :: Python :: 3
Requires-Python: >=3.7
